{
  "id": "20260517-馬斯克太空帝國進軍美股-spacex搶下-spcx-代號提前上市-最快6月12日",
  "status": "approved",
  "domain_id": "tw_market_extra",
  "domain_name": "重大頭條（股市相關）",
  "section_zh": "重大頭條",
  "section_en": "Major headlines",
  "title": "傳 SpaceX 加速那斯達克首秀，最快六月中旬以 SPCX 掛牌",
  "title_en": "Sources: SpaceX eyes earlier Nasdaq debut mid-June under SPCX",
  "source_title": "馬斯克太空帝國進軍美股！SpaceX搶下「SPCX」代號提前上市 最快6月12日掛牌那斯達克",
  "url": "https://news.cnyes.com/news/id/6460901",
  "rss_source": "Anue鉅亨",
  "created_at": "2026-05-17T09:02:55.305760+00:00",
  "site_segment": "us",
  "importance_score": 27.0,
  "approved_at": "2026-05-17T09:05:14.115812+00:00"
}