{
  "id": "20260630-2-5兆股利出籠-外資結匯壓力大-台幣恐測32元關卡",
  "status": "approved",
  "domain_id": "tw_stock",
  "domain_name": "台股與集中市場",
  "section_zh": "市場消息",
  "section_en": "Market news",
  "title": "2.5兆股利出籠！外資結匯壓力大 台幣恐測32元關卡",
  "title_en": "2.5兆股利出籠！外資結匯壓力大 台幣恐測32元關卡",
  "source_title": "2.5兆股利出籠！外資結匯壓力大 台幣恐測32元關卡",
  "url": "https://news.cnyes.com/news/id/6516672",
  "rss_source": "Anue鉅亨",
  "created_at": "2026-06-30T23:06:28.765542+00:00",
  "site_segment": "tw",
  "importance_score": 28.0,
  "approved_at": "2026-06-30T23:06:29.912443+00:00"
}