{
  "id": "20260627-stablecoinx-bets-on-ethena-ecosystem-wit",
  "status": "approved",
  "domain_id": "crypto_news",
  "domain_name": "加密貨幣與區塊鏈",
  "section_zh": "加密貨幣",
  "section_en": "Cryptocurrencies",
  "title": "StablecoinX to List on Nasdaq Amid Crypto Bear Market",
  "title_en": "StablecoinX to List on Nasdaq Amid Crypto Bear Market",
  "source_title": "StablecoinX bets on Ethena ecosystem with Nasdaq debut",
  "url": "https://cointelegraph.com/news/stablecoinx-merges-with-tlgy-and-begins-trading-on-nasdaq-friday?utm_source=rss_feed&utm_medium=rss&utm_campaign=rss_partner_inbound",
  "rss_source": "Cointelegraph.com News",
  "created_at": "2026-06-27T22:58:45.262506+00:00",
  "site_segment": "crypto",
  "importance_score": 33.5,
  "approved_at": "2026-06-27T23:03:27.184914+00:00"
}