{
  "id": "20260713-三星2奈米策略大轉彎-不再與台積電拚首發-1-4奈米延至2029年",
  "status": "approved",
  "domain_id": "us_stock",
  "domain_name": "美股與國際市場",
  "section_zh": "美股消息",
  "section_en": "U.S. & global equities",
  "title": "三星2奈米策略大轉彎？不再與台積電拚首發、1.4奈米延至2029年 |  - 歐亞股",
  "title_en": "三星2奈米策略大轉彎？不再與台積電拚首發、1.4奈米延至2029年 |  - 歐亞股",
  "source_title": "三星2奈米策略大轉彎？不再與台積電拚首發、1.4奈米延至2029年",
  "url": "https://news.cnyes.com/news/id/6531406",
  "rss_source": "Anue鉅亨",
  "created_at": "2026-07-13T04:27:45.632287+00:00",
  "site_segment": "us",
  "importance_score": 32.0,
  "approved_at": "2026-07-13T04:33:17.571500+00:00"
}