{
  "id": "20260706-bitcoin-recovers-from-strategy-s-btc-sal",
  "status": "approved",
  "domain_id": "crypto_news",
  "domain_name": "加密貨幣與區塊鏈",
  "section_zh": "加密貨幣",
  "section_en": "Cryptocurrencies",
  "title": "Bitcoin Bounces Above $63K Following Strategy-fueled Selloff",
  "title_en": "Bitcoin Bounces Above $63K Following Strategy-fueled Selloff",
  "source_title": "Bitcoin recovers from Strategy's BTC sale, funding rates hit 9%: Are bulls back?",
  "url": "https://cointelegraph.com/markets/bitcoin-recovers-from-strategy-btc-sale-funding-rates-hit-9-are-bulls-back?utm_source=rss_feed&utm_medium=rss&utm_campaign=rss_partner_inbound",
  "rss_source": "Cointelegraph.com News",
  "created_at": "2026-07-06T23:02:24.697691+00:00",
  "site_segment": "crypto",
  "importance_score": 29.5,
  "approved_at": "2026-07-06T23:03:39.656444+00:00"
}