{
  "id": "20260609-strategy-s-bitcoin-purchase-fails-to-sti",
  "status": "approved",
  "domain_id": "crypto_news",
  "domain_name": "加密貨幣與區塊鏈",
  "section_zh": "加密貨幣",
  "section_en": "Cryptocurrencies",
  "title": "Strategy's (MSTR) bitcoin purchase fails to stir BTC price: Crypto Markets Today",
  "title_en": "Strategy's (MSTR) bitcoin purchase fails to stir BTC price: Crypto Markets Today",
  "source_title": "Strategy's bitcoin purchase fails to stir BTC price",
  "url": "https://www.coindesk.com/markets/2026/06/09/strategy-s-bitcoin-purchase-fails-to-stir-btc-price",
  "rss_source": "CoinDesk: Bitcoin, Ethereum, Crypto News and Price Data",
  "created_at": "2026-06-09T12:19:11.699446+00:00",
  "site_segment": "crypto",
  "importance_score": 29.5,
  "approved_at": "2026-06-09T12:19:26.179105+00:00"
}